openhands/__init__.py
openhands/agenthub/README.md
openhands/agenthub/__init__.py
openhands/agenthub/bluelamp_agents/__init__.py
openhands/agenthub/bluelamp_agents/agent_configs.py
openhands/agenthub/bluelamp_agents/agents.py
openhands/agenthub/extension_manager_agent/README.md
openhands/agenthub/extension_manager_agent/__init__.py
openhands/agenthub/extension_manager_agent/extension_manager_agent.py
openhands/agenthub/extension_manager_agent/function_calling.py
openhands/agenthub/extension_manager_agent/prompts/additional_info.j2
openhands/agenthub/extension_manager_agent/prompts/implementation_agent_system_prompt.j2
openhands/agenthub/extension_manager_agent/prompts/in_context_learning_example.j2
openhands/agenthub/extension_manager_agent/prompts/in_context_learning_example_suffix.j2
openhands/agenthub/extension_manager_agent/prompts/microagent_info.j2
openhands/agenthub/extension_manager_agent/prompts/user_prompt.j2
openhands/agenthub/extension_manager_agent/tools/__init__.py
openhands/agenthub/extension_manager_agent/tools/bash.py
openhands/agenthub/extension_manager_agent/tools/bluelamp_delegate.py
openhands/agenthub/extension_manager_agent/tools/browser.py
openhands/agenthub/extension_manager_agent/tools/finish.py
openhands/agenthub/extension_manager_agent/tools/llm_based_edit.py
openhands/agenthub/extension_manager_agent/tools/str_replace_editor.py
openhands/agenthub/extension_manager_agent/tools/think.py
openhands/agenthub/orchestrator_agent/README.md
openhands/agenthub/orchestrator_agent/__init__.py
openhands/agenthub/orchestrator_agent/function_calling.py
openhands/agenthub/orchestrator_agent/orchestrator_agent.py
openhands/agenthub/orchestrator_agent/prompts/additional_info.j2
openhands/agenthub/orchestrator_agent/prompts/in_context_learning_example.j2
openhands/agenthub/orchestrator_agent/prompts/in_context_learning_example_suffix.j2
openhands/agenthub/orchestrator_agent/prompts/microagent_info.j2
bluelamp_ai-1.3.1.dist-info/METADATA
bluelamp_ai-1.3.1.dist-info/WHEEL
bluelamp_ai-1.3.1.dist-info/entry_points.txt
bluelamp_ai-1.3.1.dist-info/RECORD
