Metadata-Version: 2.3
Name: bluelamp-ai
Version: 1.3.1
Summary: BlueLamp AI: 日本語対応AIエージェントシステム - オーケストレーターと拡張マネージャー（最新版）
License: MIT
Keywords: ai,agent,japanese,automation,development
Author: BlueLamp Team
Requires-Python: >=3.10
Classifier: Development Status :: 5 - Production/Stable
Classifier: Intended Audience :: Developers
Classifier: License :: OSI Approved :: MIT License
Classifier: Natural Language :: Japanese
Classifier: Programming Language :: Python :: 3
Classifier: Programming Language :: Python :: 3.10
Classifier: Programming Language :: Python :: 3.11
Classifier: Programming Language :: Python :: 3.12
Classifier: Programming Language :: Python :: 3.13
Classifier: Topic :: Scientific/Engineering :: Artificial Intelligence
Classifier: Topic :: Software Development :: Code Generators
Requires-Dist: PyPDF2
Requires-Dist: aiohttp (>=3.9.0,!=3.11.13)
Requires-Dist: anthropic[vertex]
Requires-Dist: anyio (==4.9.0)
Requires-Dist: bashlex (>=0.18,<0.19)
Requires-Dist: boto3
Requires-Dist: daytona (==0.21.1)
Requires-Dist: dirhash
Requires-Dist: docker
Requires-Dist: fastapi
Requires-Dist: fastmcp (>=2.5.2,<3.0.0)
Requires-Dist: google-api-python-client (>=2.164.0,<3.0.0)
Requires-Dist: google-auth-httplib2
Requires-Dist: google-auth-oauthlib
Requires-Dist: google-cloud-aiplatform
Requires-Dist: google-generativeai
Requires-Dist: html2text
Requires-Dist: ipywidgets (>=8.1.5,<9.0.0)
Requires-Dist: jinja2 (>=3.1.3,<4.0.0)
Requires-Dist: joblib
Requires-Dist: json-repair
Requires-Dist: kubernetes (>=33.1.0,<34.0.0)
Requires-Dist: libtmux (>=0.37,<0.40)
Requires-Dist: litellm (>=1.60.0,<2.0.0,!=1.64.4,!=1.67.*)
Requires-Dist: minio (>=7.2.8,<8.0.0)
Requires-Dist: numpy
Requires-Dist: openhands_aci (==0.3.0)
Requires-Dist: opentelemetry-api (>=1.33.1,<2.0.0)
Requires-Dist: opentelemetry-exporter-otlp-proto-grpc (>=1.33.1,<2.0.0)
Requires-Dist: pathspec (>=0.12.1,<0.13.0)
Requires-Dist: pexpect
Requires-Dist: poetry (>=2.1.2,<3.0.0)
Requires-Dist: prompt-toolkit (>=3.0.50,<4.0.0)
Requires-Dist: protobuf (>=5.0.0,<6.0.0)
Requires-Dist: psutil
Requires-Dist: pygithub (>=2.5.0,<3.0.0)
Requires-Dist: pyjwt (>=2.9.0,<3.0.0)
Requires-Dist: pylatexenc
Requires-Dist: python-docx
Requires-Dist: python-dotenv
Requires-Dist: python-frontmatter (>=1.1.0,<2.0.0)
Requires-Dist: python-json-logger (>=3.2.1,<4.0.0)
Requires-Dist: python-pptx
Requires-Dist: pythonnet
Requires-Dist: pyyaml (>=6.0.2,<7.0.0)
Requires-Dist: qtconsole (>=5.6.1,<6.0.0)
Requires-Dist: rapidfuzz (>=3.9.0,<4.0.0)
Requires-Dist: redis (>=5.2,<7.0)
Requires-Dist: sse-starlette (>=2.1.3,<3.0.0)
Requires-Dist: stripe (>=11.5,<13.0)
Requires-Dist: tenacity (>=8.5,<10.0)
Requires-Dist: termcolor
Requires-Dist: toml
Requires-Dist: types-toml
Requires-Dist: whatthepatch (>=1.0.6,<2.0.0)
Requires-Dist: zope-interface (==7.2)
Project-URL: Repository, https://github.com/your-repo/bluelamp-ai
